jodel_api/__init__.py
jodel_api/gcmhack.py
jodel_api/jodel_api.py
jodel_api/protos/__init__.py
jodel_api/protos/checkin_pb2.py
jodel_api/protos/mcs_pb2.py
jodel_api-1.2.11.dist-info/DESCRIPTION.rst
jodel_api-1.2.11.dist-info/METADATA
jodel_api-1.2.11.dist-info/RECORD
jodel_api-1.2.11.dist-info/WHEEL
jodel_api-1.2.11.dist-info/metadata.json
jodel_api-1.2.11.dist-info/top_level.txt
