Metadata-Version: 2.0
Name: jodel-api
Version: 1.2.11
Summary: Unoffical Python Interface to the Jodel API
Home-page: https://github.com/nborrmann/jodel_api
Author: Nils Borrmann
Author-email: n.borrmann@googlemail.com
License: MIT
Keywords: jodel
Platform: UNKNOWN
Classifier: Development Status :: 5 - Production/Stable
Classifier: License :: OSI Approved :: MIT License
Classifier: Intended Audience :: Developers
Classifier: Programming Language :: Python :: 2
Classifier: Programming Language :: Python :: 2.7
Classifier: Programming Language :: Python :: 3
Classifier: Programming Language :: Python :: 3.3
Classifier: Programming Language :: Python :: 3.4
Classifier: Programming Language :: Python :: 3.5
Classifier: Topic :: Internet :: WWW/HTTP
Classifier: Topic :: Internet :: WWW/HTTP :: Dynamic Content :: Message Boards
Classifier: Topic :: Software Development :: Libraries :: Python Modules
Requires-Dist: requests
Requires-Dist: future
Requires-Dist: mock
Requires-Dist: varint
Requires-Dist: protobuf
